[
  {
    "id": "e68278cc-10b5-4ac1-932f-adec66e38ffa",
    "is_public": true,
    "is_featured": false,
    "status": "published",
    "published_at": "2025-09-11T08:43:40.724911+00:00",
    "seo_noindex": false,
    "seo_nofollow": false,
    "seo_title": "",
    "seo_description": "",
    "seo_canonical_url": "",
    "seo_og_image_url": "",
    "views_count": 25,
    "download_count": 2,
    "created_by": "63268e9f-91a9-4d0e-9b22-4130e171846b",
    "created_at": "2025-09-11T08:43:11.787674+00:00",
    "updated_at": "2025-10-03T02:03:42.640039+00:00",
    "search_vector": "'2023':16B,109B '2027':18B,111B '4380':193 'a158':195 'a158-bc063339a9b9':194 'a7da92c9':191 'a7da92c9-b726':190 'access':46B,139B 'achiev':56B,149B 'afford':49B,142B 'author':7B,100B 'b726':192 'bc063339a9b9':196 'close':66B,159B 'continu':63B,156B 'corpor':2A,10B,103B 'critic':54B,147B 'develop':29B,59B,92B,122B,152B,185B 'distribut':85B,178B 'drive':31B,124B 'econom':32B,125B 'effici':88B,181B 'energi':6B,25B,52B,82B,87B,95B,99B,118B,145B,175B,180B,188B 'enhanc':24B,117B 'first':9B,102B 'generat':83B,176B 'goal':60B,153B 'ground':41B,134B 'growth':33B,126B 'guinea':37B,130B 'improv':86B,179B 'increas':81B,174B 'innov':78B,171B 'lay':19B,112B 'nation':5B,58B,98B,151B 'nea':1A 'new':36B,129B 'papua':35B,128B 'partner':69B,162B 'period':14B,107B 'plan':3A,11B,104B 'privat':74B,167B 'promot':27B,90B,120B,183B 'public':72B,165B 'pursu':77B,170B 'recognit':44B,137B 'reliabl':48B,141B 'renew':94B,187B 'sector':75B,168B 'secur':26B,119B 'solut':79B,172B 'sourc':96B,189B 'strategi':39B,132B 'sustain':28B,51B,121B,144B 'vision':22B,115B 'work':65B,158B",
    "title": "NEA Corporate Plan",
    "slug": "nea-corporate-plan",
    "excerpt": "<p>The National Energy Authority's first Corporate Plan for the period from 2023 to 2027 lays out our vision to enhance energy security, promote sustainable development, and drive economic growth in Papua New Guinea. Our strategy is grounded in the recognition that access to reliable, affordable, and sustainable energy is critical to achieving our national development goals. We will continue to work closely with our partners in the public and private sectors to pursue innovative solutions that increase energy generation and distribution, improve energy efficiency, and promote the development of renewable energy sources.</p>",
    "description": "<p>The National Energy Authority's first Corporate Plan for the period from 2023 to 2027 lays out our vision to enhance energy security, promote sustainable development, and drive economic growth in Papua New Guinea. Our strategy is grounded in the recognition that access to reliable, affordable, and sustainable energy is critical to achieving our national development goals. We will continue to work closely with our partners in the public and private sectors to pursue innovative solutions that increase energy generation and distribution, improve energy efficiency, and promote the development of renewable energy sources.</p>",
    "author": "",
    "file_url": "https://uezenrqnuuaglgwnvbsx.supabase.co/storage/v1/object/public/site-assets/resources/1759043386146-NEA%20Corporate%20Plan%20-%20Final%20v9%20160724.pdf",
    "file_type": "application/pdf",
    "external_url": "",
    "tags": [],
    "categories": [
      "a7da92c9-b726-4380-a158-bc063339a9b9"
    ],
    "resource_types": [
      "b44e7a6f-6796-4ec7-a958-4cf55638845c"
    ],
    "categories_backup": [],
    "sections": [
      {
        "id": "6f6e5fa6-30d3-4295-b26e-e7f42a59948c",
        "title": "",
        "layout": "single",
        "content": "[news-grid show_title=\"true\" show_description=\"true\" title_size=\"xl\" title_align=\"left\" title_color=\"default\" cols=\"1\" md_cols=\"2\" lg_cols=\"2\" gap=\"md\" card_variant=\"elevated\" background=\"transparent\" padding=\"md\" enable_search=\"false\" enable_filters=\"false\" featured_only=\"false\" sort_dir=\"desc\" limit=\"6\" load_more=\"true\" show_view_all=\"false\" /]",
        "imageUrl": "",
        "gridItems": [],
        "showTitle": true,
        "heroConfig": {
          "height": "lg",
          "enabled": true,
          "gradientTo": "hsl(var(--primary-foreground))",
          "gradientFrom": "hsl(var(--primary))",
          "backgroundType": "gradient",
          "overlayOpacity": 0.2,
          "gradientDirection": "to-br",
          "backgroundImageFit": "cover",
          "backgroundImageUrl": "",
          "backgroundImagePosition": "center"
        },
        "titleStyle": {
          "font": "sans",
          "size": "md",
          "align": "left",
          "color": "default",
          "weight": "bold",
          "tracking": "normal",
          "transform": "normal"
        },
        "gridColumns": 3,
        "subtitleStyle": {
          "font": "sans",
          "size": "sm",
          "align": "center",
          "color": "white",
          "weight": "normal",
          "tracking": "normal",
          "transform": "normal"
        }
      }
    ],
    "featured_image_url": "https://uezenrqnuuaglgwnvbsx.supabase.co/storage/v1/object/public/site-assets/1759043120642-nea_coporate_plan.png",
    "deleted_at": null,
    "deleted_by": null,
    "shares_count": 0,
    "audio_enabled": true,
    "audio_voice": "female",
    "audio_generated_at": null
  },
  {
    "id": "4b9f3671-2bc9-4659-b3df-d033ba86cf19",
    "is_public": true,
    "is_featured": false,
    "status": "published",
    "published_at": "2025-09-11T08:42:27.561129+00:00",
    "seo_noindex": false,
    "seo_nofollow": false,
    "seo_title": "",
    "seo_description": "",
    "seo_canonical_url": "",
    "seo_og_image_url": "",
    "views_count": 15,
    "download_count": 1,
    "created_by": "63268e9f-91a9-4d0e-9b22-4130e171846b",
    "created_at": "2025-09-11T08:42:06.813229+00:00",
    "updated_at": "2025-09-30T22:44:49.258166+00:00",
    "search_vector": "'action':53B,88B 'ambitl':14A 'area':50B,85B 'critic':32B,67B 'data':30B,65B 'date':27B,62B 'deforest':29B,64B 'field':7A,8A 'geochemistri':12A 'geotherm':1A,6A 'global':28B,63B 'guinea':18A 'help':41B,76B 'highlight':31B,66B 'hotspot':33B,68B 'identifi':49B,84B 'intend':39B,74B 'interact':20B,55B 'investig':9A 'island':15A 'map':37B,72B 'new':17A 'ngos':43B,78B 'papua':16A 'policymak':42B,77B 'progress':47B,82B 'prospect':2A 'provid':23B,58B 'requir':51B,86B 'research':45B,80B 'resourc':21B,56B 'track':46B,81B 'trend':35B,70B 'tropic':5A 'up-to-d':24B,59B 'urgent':52B,87B 'water':11A",
    "title": "Geothermal prospecting of a tropical geothermal field \u2013 field investigation and water geochemistry of Ambitle Island, Papua New Guinea",
    "slug": "geothermal-prospecting-of-a-tropical-geothermal-field-field-investigation-and-water-geochemistry-of-ambitle-island-papua-new-guinea",
    "excerpt": "<p>An interactive resource that provides up-to-date global deforestation data, highlighting critical hotspots and trends. The map is intended to help policymakers, NGOs, and researchers track progress and identify areas requiring urgent action.</p>",
    "description": "<p>An interactive resource that provides up-to-date global deforestation data, highlighting critical hotspots and trends. The map is intended to help policymakers, NGOs, and researchers track progress and identify areas requiring urgent action.</p>",
    "author": "",
    "file_url": "https://uezenrqnuuaglgwnvbsx.supabase.co/storage/v1/object/public/site-assets/resources/1759131733491-Geothermal%20prospecting%20of%20a%20tropical%20geothermal%20field%20%20%20field%20investigation%20and%20water%20geochemistry%20of%20Ambitle%20Island%20%20Papua%20New%20Guinea.pdf",
    "file_type": "application/pdf",
    "external_url": "",
    "tags": [],
    "categories": [],
    "resource_types": [
      "266e2d60-d111-4eb1-98d0-341a103b903c"
    ],
    "categories_backup": [],
    "sections": [],
    "featured_image_url": "https://uezenrqnuuaglgwnvbsx.supabase.co/storage/v1/object/public/site-assets/1759132178610-Geothermal-Field.jpg",
    "deleted_at": null,
    "deleted_by": null,
    "shares_count": 0,
    "audio_enabled": true,
    "audio_voice": "female",
    "audio_generated_at": null
  }
]